signatureanalyzer/__init__.py
signatureanalyzer/__main__.py
signatureanalyzer/bnmf.py
signatureanalyzer/consensus.py
signatureanalyzer/context.py
signatureanalyzer/signatureanalyzer.py
signatureanalyzer/spectra.py
signatureanalyzer/supervised_bnmf.py
signatureanalyzer/utils.py
signatureanalyzer/pathways/__init__.py
signatureanalyzer/pathways/_gsea.py
signatureanalyzer/plotting/__init__.py
signatureanalyzer/plotting/_cosine.py
signatureanalyzer/plotting/_muts.py
signatureanalyzer/plotting/_nmf.py
signatureanalyzer/plotting/_rna.py
signatureanalyzer/plotting/_utils.py
signatureanalyzer/ref/cosmic_v2/sa_cosmic2.tsv
signatureanalyzer/ref/cosmic_v3/sa_cosmic3_dbs.tsv
signatureanalyzer/ref/cosmic_v3/sa_cosmic3_id.tsv
signatureanalyzer/ref/cosmic_v3/sa_cosmic3_sbs.tsv
signatureanalyzer/ref/cosmic_v3/sa_cosmic3_sbs_exome.tsv
signatureanalyzer/ref/cosmic_v3/sa_cosmic3_sbs_t.tsv
signatureanalyzer-0.0.8.dist-info/LICENSE
signatureanalyzer-0.0.8.dist-info/METADATA
signatureanalyzer-0.0.8.dist-info/WHEEL
signatureanalyzer-0.0.8.dist-info/entry_points.txt
signatureanalyzer-0.0.8.dist-info/top_level.txt
signatureanalyzer-0.0.8.dist-info/RECORD
