Metadata-Version: 2.1
Name: signatureanalyzer
Version: 0.0.8
Summary: Bayesian NMF methods for mutational signature analysis & transcriptomic profiling on GPUs (Getz Lab).
Home-page: https://github.com/broadinstitute/getzlab-SignatureAnalyzer
Author: Shankara Anand & Justin Cha - Broad Institute - Cancer Genome Computational Analysis
Author-email: sanand@broadinstitute.org
License: MIT
Classifier: Development Status :: 3 - Alpha
Classifier: Programming Language :: Python :: 3
Classifier: Intended Audience :: Science/Research
Classifier: Topic :: Scientific/Engineering :: Bio-Informatics
Classifier: Topic :: Scientific/Engineering :: Interface Engine/Protocol Translator
License-File: LICENSE
Requires-Dist: gprofiler
Requires-Dist: h5py (>=2.9.0)
Requires-Dist: matplotlib
Requires-Dist: numpy (<1.24.0)
Requires-Dist: pandas (>=0.25.0)
Requires-Dist: pyarrow (>=0.14.1)
Requires-Dist: scikit-image (>=0.15.0)
Requires-Dist: scikit-learn (>=0.21.3)
Requires-Dist: scipy
Requires-Dist: seaborn (>=0.9.0)
Requires-Dist: tables (>=3.6.1)
Requires-Dist: torch (>=1.2.0)
Requires-Dist: tqdm (>=4.33.0)
Requires-Dist: twobitreader (>=3.1.7)
